pgzrun.py
pgzero/__init__.py
pgzero/__main__.py
pgzero/actor.py
pgzero/animation.py
pgzero/builtins.py
pgzero/clock.py
pgzero/constants.py
pgzero/game.py
pgzero/keyboard.py
pgzero/loaders.py
pgzero/music.py
pgzero/ptext.py
pgzero/rect.py
pgzero/runner.py
pgzero/screen.py
pgzero/soundfmt.py
pgzero/spellcheck.py
pgzero/tone.py
pgzero/data/icon.png
pgzero/data/joypad.png
pgzero-1.2.dist-info/DESCRIPTION.rst
pgzero-1.2.dist-info/METADATA
pgzero-1.2.dist-info/RECORD
pgzero-1.2.dist-info/WHEEL
pgzero-1.2.dist-info/entry_points.txt
pgzero-1.2.dist-info/metadata.json
pgzero-1.2.dist-info/top_level.txt
