Metadata-Version: 1.1
Name: pgzero
Version: 1.2
Summary: A zero-boilerplate 2D games framework
Home-page: http://pypi.python.org/pypi/pgzero
Author: Daniel Pope
Author-email: mauve@mauveweb.co.uk
License: UNKNOWN
Platform: UNKNOWN
Classifier: Development Status :: 5 - Production/Stable
Classifier: Intended Audience :: Education
Classifier: License :: OSI Approved :: GNU Lesser General Public License v3 (LGPLv3)
Classifier: Programming Language :: Python :: 3 :: Only
Classifier: Topic :: Education
Classifier: Topic :: Games/Entertainment
